AUTHORS.rst
CHANGELOG.rst
LICENSE
MANIFEST.in
README.rst
setup.py
jmbo_analytics/__init__.py
jmbo_analytics/middleware.py
jmbo_analytics/models.py
jmbo_analytics/settings.py
jmbo_analytics/tasks.py
jmbo_analytics/urls.py
jmbo_analytics/utils.py
jmbo_analytics.egg-info/PKG-INFO
jmbo_analytics.egg-info/SOURCES.txt
jmbo_analytics.egg-info/dependency_links.txt
jmbo_analytics.egg-info/not-zip-safe
jmbo_analytics.egg-info/requires.txt
jmbo_analytics.egg-info/top_level.txt
jmbo_analytics/templatetags/__init__.py
jmbo_analytics/templatetags/__init__.pyc
jmbo_analytics/templatetags/jmbo_analytics_tags.py
jmbo_analytics/templatetags/jmbo_analytics_tags.pyc
jmbo_analytics/tests/__init__.py
jmbo_analytics/tests/__init__.pyc
jmbo_analytics/tests/requirements.txt
jmbo_analytics/views/__init__.py
jmbo_analytics/views/__init__.pyc
jmbo_analytics/views/google_analytics.py
jmbo_analytics/views/google_analytics.pyc